<?xml version="1.0"?>
<!--<!DOCTYPE metadata SYSTEM "http://www.esri.com/metadata/esriprof80.dtd">-->
<metadata xml:lang="en"><Esri><MetaID>{7ADF0370-3421-4B0E-BF87-4D7AF5752BE2}</MetaID><CreaDate>20100906</CreaDate><CreaTime>22453200</CreaTime><SyncOnce>TRUE</SyncOnce><DataProperties><lineage><Process ToolSource="C:\Program Files\ArcGIS\ArcToolbox\Toolboxes\Spatial Analyst Tools.tbx\Int" Date="20100906" Time="224532">Int M:\Andriy\new_run\scripts_new_improved\tmp\afr_level1 M:\Andriy\new_run\scripts_new_improved\tmp\combine</Process><Process ToolSource="C:\Program Files\ArcGIS\ArcToolbox\Toolboxes\Data Management Tools.tbx\BuildRasterAttributeTable" Date="20100906" Time="224534">BuildRasterAttributeTable M:\Andriy\new_run\scripts_new_improved\tmp\combine Overwrite M:\Andriy\new_run\scripts_new_improved\tmp\combine</Process><Process ToolSource="C:\Program Files\ArcGIS\ArcToolbox\Toolboxes\Data Management Tools.tbx\BuildRasterAttributeTable" Date="20100906" Time="225751">BuildRasterAttributeTable M:\Andriy\new_run\scripts_new_improved\tmp\combine Overwrite M:\Andriy\new_run\scripts_new_improved\tmp\combine</Process><Process ToolSource="C:\Program Files\ArcGIS\ArcToolbox\Toolboxes\Data Management Tools.tbx\AddField" Date="20100906" Time="225752">AddField M:\Andriy\new_run\scripts_new_improved\tmp\combine CLASS_31 LONG # # # # NULLABLE REQUIRED # M:\Andriy\new_run\scripts_new_improved\tmp\combine</Process><Process ToolSource="C:\Program Files\ArcGIS\ArcToolbox\Toolboxes\Data Management Tools.tbx\AddField" Date="20100906" Time="225755">AddField M:\Andriy\new_run\scripts_new_improved\tmp\combine CLASS_30 LONG # # # # NULLABLE REQUIRED # M:\Andriy\new_run\scripts_new_improved\tmp\combine</Process><Process ToolSource="C:\Program Files\ArcGIS\ArcToolbox\Toolboxes\Data Management Tools.tbx\AddField" Date="20100906" Time="225758">AddField M:\Andriy\new_run\scripts_new_improved\tmp\combine CLASS_29 LONG # # # # NULLABLE REQUIRED # M:\Andriy\new_run\scripts_new_improved\tmp\combine</Process><Process ToolSource="C:\Program Files\ArcGIS\ArcToolbox\Toolboxes\Data Management Tools.tbx\AddField" Date="20100906" Time="225801">AddField M:\Andriy\new_run\scripts_new_improved\tmp\combine CLASS_28 LONG # # # # NULLABLE REQUIRED # M:\Andriy\new_run\scripts_new_improved\tmp\combine</Process><Process ToolSource="C:\Program Files\ArcGIS\ArcToolbox\Toolboxes\Data Management Tools.tbx\AddField" Date="20100906" Time="225804">AddField M:\Andriy\new_run\scripts_new_improved\tmp\combine CLASS_27 LONG # # # # NULLABLE REQUIRED # M:\Andriy\new_run\scripts_new_improved\tmp\combine</Process><Process ToolSource="C:\Program Files\ArcGIS\ArcToolbox\Toolboxes\Data Management Tools.tbx\AddField" Date="20100906" Time="225807">AddField M:\Andriy\new_run\scripts_new_improved\tmp\combine CLASS_26 LONG # # # # NULLABLE REQUIRED # M:\Andriy\new_run\scripts_new_improved\tmp\combine</Process><Process ToolSource="C:\Program Files\ArcGIS\ArcToolbox\Toolboxes\Data Management Tools.tbx\AddField" Date="20100906" Time="225810">AddField M:\Andriy\new_run\scripts_new_improved\tmp\combine CLASS_25 LONG # # # # NULLABLE REQUIRED # M:\Andriy\new_run\scripts_new_improved\tmp\combine</Process><Process ToolSource="C:\Program Files\ArcGIS\ArcToolbox\Toolboxes\Data Management Tools.tbx\AddField" Date="20100906" Time="225813">AddField M:\Andriy\new_run\scripts_new_improved\tmp\combine CLASS_24 LONG # # # # NULLABLE REQUIRED # M:\Andriy\new_run\scripts_new_improved\tmp\combine</Process><Process ToolSource="C:\Program Files\ArcGIS\ArcToolbox\Toolboxes\Data Management Tools.tbx\AddField" Date="20100906" Time="225816">AddField M:\Andriy\new_run\scripts_new_improved\tmp\combine CLASS_23 LONG # # # # NULLABLE REQUIRED # M:\Andriy\new_run\scripts_new_improved\tmp\combine</Process><Process ToolSource="C:\Program Files\ArcGIS\ArcToolbox\Toolboxes\Data Management Tools.tbx\AddField" Date="20100906" Time="225819">AddField M:\Andriy\new_run\scripts_new_improved\tmp\combine CLASS_22 LONG # # # # NULLABLE REQUIRED # M:\Andriy\new_run\scripts_new_improved\tmp\combine</Process><Process ToolSource="C:\Program Files\ArcGIS\ArcToolbox\Toolboxes\Data Management Tools.tbx\AddField" Date="20100906" Time="225822">AddField M:\Andriy\new_run\scripts_new_improved\tmp\combine CLASS_21 LONG # # # # NULLABLE REQUIRED # M:\Andriy\new_run\scripts_new_improved\tmp\combine</Process><Process ToolSource="C:\Program Files\ArcGIS\ArcToolbox\Toolboxes\Data Management Tools.tbx\AddField" Date="20100906" Time="225825">AddField M:\Andriy\new_run\scripts_new_improved\tmp\combine CLASS_20 LONG # # # # NULLABLE REQUIRED # M:\Andriy\new_run\scripts_new_improved\tmp\combine</Process><Process ToolSource="C:\Program Files\ArcGIS\ArcToolbox\Toolboxes\Data Management Tools.tbx\AddField" Date="20100906" Time="225828">AddField M:\Andriy\new_run\scripts_new_improved\tmp\combine CLASS_19 LONG # # # # NULLABLE REQUIRED # M:\Andriy\new_run\scripts_new_improved\tmp\combine</Process><Process ToolSource="C:\Program Files\ArcGIS\ArcToolbox\Toolboxes\Data Management Tools.tbx\AddField" Date="20100906" Time="225831">AddField M:\Andriy\new_run\scripts_new_improved\tmp\combine CLASS_18 LONG # # # # NULLABLE REQUIRED # M:\Andriy\new_run\scripts_new_improved\tmp\combine</Process><Process ToolSource="C:\Program Files\ArcGIS\ArcToolbox\Toolboxes\Data Management Tools.tbx\AddField" Date="20100906" Time="225834">AddField M:\Andriy\new_run\scripts_new_improved\tmp\combine CLASS_17 LONG # # # # NULLABLE REQUIRED # M:\Andriy\new_run\scripts_new_improved\tmp\combine</Process><Process ToolSource="C:\Program Files\ArcGIS\ArcToolbox\Toolboxes\Data Management Tools.tbx\AddField" Date="20100906" Time="225837">AddField M:\Andriy\new_run\scripts_new_improved\tmp\combine CLASS_16 LONG # # # # NULLABLE REQUIRED # M:\Andriy\new_run\scripts_new_improved\tmp\combine</Process><Process ToolSource="C:\Program Files\ArcGIS\ArcToolbox\Toolboxes\Data Management Tools.tbx\AddField" Date="20100906" Time="225840">AddField M:\Andriy\new_run\scripts_new_improved\tmp\combine CLASS_15 LONG # # # # NULLABLE REQUIRED # M:\Andriy\new_run\scripts_new_improved\tmp\combine</Process><Process ToolSource="C:\Program Files\ArcGIS\ArcToolbox\Toolboxes\Data Management Tools.tbx\AddField" Date="20100906" Time="225843">AddField M:\Andriy\new_run\scripts_new_improved\tmp\combine CLASS_14 LONG # # # # NULLABLE REQUIRED # M:\Andriy\new_run\scripts_new_improved\tmp\combine</Process><Process ToolSource="C:\Program Files\ArcGIS\ArcToolbox\Toolboxes\Data Management Tools.tbx\AddField" Date="20100906" Time="225846">AddField M:\Andriy\new_run\scripts_new_improved\tmp\combine CLASS_13 LONG # # # # NULLABLE REQUIRED # M:\Andriy\new_run\scripts_new_improved\tmp\combine</Process><Process ToolSource="C:\Program Files\ArcGIS\ArcToolbox\Toolboxes\Data Management Tools.tbx\AddField" Date="20100906" Time="225849">AddField M:\Andriy\new_run\scripts_new_improved\tmp\combine CLASS_12 LONG # # # # NULLABLE REQUIRED # M:\Andriy\new_run\scripts_new_improved\tmp\combine</Process><Process ToolSource="C:\Program Files\ArcGIS\ArcToolbox\Toolboxes\Data Management Tools.tbx\AddField" Date="20100906" Time="225852">AddField M:\Andriy\new_run\scripts_new_improved\tmp\combine CLASS_11 LONG # # # # NULLABLE REQUIRED # M:\Andriy\new_run\scripts_new_improved\tmp\combine</Process><Process ToolSource="C:\Program Files\ArcGIS\ArcToolbox\Toolboxes\Data Management Tools.tbx\AddField" Date="20100906" Time="225855">AddField M:\Andriy\new_run\scripts_new_improved\tmp\combine CLASS_10 LONG # # # # NULLABLE REQUIRED # M:\Andriy\new_run\scripts_new_improved\tmp\combine</Process><Process ToolSource="C:\Program Files\ArcGIS\ArcToolbox\Toolboxes\Data Management Tools.tbx\AddField" Date="20100906" Time="225858">AddField M:\Andriy\new_run\scripts_new_improved\tmp\combine CLASS_9 LONG # # # # NULLABLE REQUIRED # M:\Andriy\new_run\scripts_new_improved\tmp\combine</Process><Process ToolSource="C:\Program Files\ArcGIS\ArcToolbox\Toolboxes\Data Management Tools.tbx\AddField" Date="20100906" Time="225901">AddField M:\Andriy\new_run\scripts_new_improved\tmp\combine CLASS_8 LONG # # # # NULLABLE REQUIRED # M:\Andriy\new_run\scripts_new_improved\tmp\combine</Process><Process ToolSource="C:\Program Files\ArcGIS\ArcToolbox\Toolboxes\Data Management Tools.tbx\AddField" Date="20100906" Time="225904">AddField M:\Andriy\new_run\scripts_new_improved\tmp\combine CLASS_7 LONG # # # # NULLABLE REQUIRED # M:\Andriy\new_run\scripts_new_improved\tmp\combine</Process><Process ToolSource="C:\Program Files\ArcGIS\ArcToolbox\Toolboxes\Data Management Tools.tbx\AddField" Date="20100906" Time="225907">AddField M:\Andriy\new_run\scripts_new_improved\tmp\combine CLASS_6 LONG # # # # NULLABLE REQUIRED # M:\Andriy\new_run\scripts_new_improved\tmp\combine</Process><Process ToolSource="C:\Program Files\ArcGIS\ArcToolbox\Toolboxes\Data Management Tools.tbx\AddField" Date="20100906" Time="225910">AddField M:\Andriy\new_run\scripts_new_improved\tmp\combine CLASS_5 LONG # # # # NULLABLE REQUIRED # M:\Andriy\new_run\scripts_new_improved\tmp\combine</Process><Process ToolSource="C:\Program Files\ArcGIS\ArcToolbox\Toolboxes\Data Management Tools.tbx\AddField" Date="20100906" Time="225914">AddField M:\Andriy\new_run\scripts_new_improved\tmp\combine CLASS_4 LONG # # # # NULLABLE REQUIRED # M:\Andriy\new_run\scripts_new_improved\tmp\combine</Process><Process ToolSource="C:\Program Files\ArcGIS\ArcToolbox\Toolboxes\Data Management Tools.tbx\AddField" Date="20100906" Time="225917">AddField M:\Andriy\new_run\scripts_new_improved\tmp\combine CLASS_3 LONG # # # # NULLABLE REQUIRED # M:\Andriy\new_run\scripts_new_improved\tmp\combine</Process><Process ToolSource="C:\Program Files\ArcGIS\ArcToolbox\Toolboxes\Data Management Tools.tbx\AddField" Date="20100906" Time="225920">AddField M:\Andriy\new_run\scripts_new_improved\tmp\combine CLASS_2 LONG # # # # NULLABLE REQUIRED # M:\Andriy\new_run\scripts_new_improved\tmp\combine</Process><Process ToolSource="C:\Program Files\ArcGIS\ArcToolbox\Toolboxes\Data Management Tools.tbx\AddField" Date="20100906" Time="225923">AddField M:\Andriy\new_run\scripts_new_improved\tmp\combine CLASS_1 LONG # # # # NULLABLE REQUIRED # M:\Andriy\new_run\scripts_new_improved\tmp\combine</Process><Process ToolSource="C:\Program Files\ArcGIS\ArcToolbox\Toolboxes\Data Management Tools.tbx\BuildRasterAttributeTable" Date="20100906" Time="225928">BuildRasterAttributeTable M:\Andriy\new_run\scripts_new_improved\tmp\combine Overwrite M:\Andriy\new_run\scripts_new_improved\tmp\combine</Process><Process ToolSource="C:\Program Files\ArcGIS\ArcToolbox\Toolboxes\Data Management Tools.tbx\AddField" Date="20100906" Time="225930">AddField M:\Andriy\new_run\scripts_new_improved\tmp\combine CLOSEST_SUM LONG # # # # NULLABLE REQUIRED # M:\Andriy\new_run\scripts_new_improved\tmp\combine</Process><Process ToolSource="C:\Program Files\ArcGIS\ArcToolbox\Toolboxes\Data Management Tools.tbx\AddField" Date="20100906" Time="225931">AddField M:\Andriy\new_run\scripts_new_improved\tmp\combine CLOSEST_CLASS LONG # # # # NULLABLE REQUIRED # M:\Andriy\new_run\scripts_new_improved\tmp\combine</Process></lineage></DataProperties></Esri></metadata>
